<?xml version="1.0" encoding="utf-8"?>
<fifowml lang="zh-TW" version="1.1-beta">
<head><product><title></title><version></version></product><source><copyright>本檔案的內容，包括但不限於所有文本、平面圖像、圖畫、圖片、照片以及數據或其他資料的匯編，均受版權保障。中央氣象局是本檔案內所有版權作品的擁有人，除非預先得到中央氣象局的書面授權，否則嚴禁複製、改編、分發、發布或向公眾提供該等版權作品。</copyright><disclaimer>中央氣象局（包括其僱員及代理人）對於本檔案所載資料的準確性、可用性、完整性或效用，概不作出明確或暗示的保證、聲明或陳述；在法律許可的範圍內，對於提供或使用這些資料而可能直接或間接引致任何損失、損壞或傷害（包括死亡），亦不負任何法律承擔或責任（包括疏忽責任）。</disclaimer><provider>中央氣象局</provider><remarks>歡迎向中央氣象局申請授權發布或向公眾提供本檔案的內容。如有任何查詢，請電郵(webqry@cwb.gov.tw)或傳真(02-23491212)至預報中心。</remarks></source><issue-time>2014-09-25T06:57:31+08:00</issue-time><updated>2014-09-25T06:57:31+08:00</updated></head>
<data category="WeatherAssistant">
<cityid>10002</cityid>
<name>宜蘭縣</name>
<stno>46708</stno>
<time>2014/9/25 上午 07:02:30</time>
<memo>鋒面影響，多雲短暫陣雨。</memo>
<memo> </memo>
<memo>昨(24)日宜蘭地區為多雲有短暫陣雨的天氣，午後山區有強降雨發生，太平山及古魯降雨超過50毫米。宜蘭市白天測得最高溫為28.4度、太平山為18.8度。夜間受鋒面逐漸接近影響，天氣為多雲短暫陣雨，溫度部分，平地最低溫23度、太平山13.9度。</memo>
<memo>今(25)日宜蘭地區受鋒面通過影響天氣轉為多雲短暫陣雨，降雨機率平地為70%、太平山為100％；氣溫部分，平地預測25~30度、太平山14~20度。</memo>
<memo>在沿岸及海上風浪部份： </memo>
<memo>宜蘭蘇澳沿海預測今日天氣為多雲局部陣雨或雷雨；風向偏南風明轉偏東風；風浪為小浪，風力4級陣風6級以下。</memo>
<memo>海岸邊以蘇澳為例，今日天氣為多雲短暫陣雨，降雨機率80％，氣溫25~29度，風力2級。</memo>
</data>
</fifowml>
